voxium-0.2.0.dist-info/licenses/LICENSE
voxium_client/__init__.py
voxium_client/client.py
voxium_client/live_transcribe.py
voxium-0.2.0.dist-info/METADATA
voxium-0.2.0.dist-info/WHEEL
voxium-0.2.0.dist-info/top_level.txt
voxium-0.2.0.dist-info/RECORD
